idds/__init__.py
idds/common/__init__.py
idds/common/authentication.py
idds/common/cache.py
idds/common/config.py
idds/common/constants.py
idds/common/dict_class.py
idds/common/event.py
idds/common/exceptions.py
idds/common/status_utils.py
idds/common/utils.py
idds/common/version.py
idds/common/plugin/__init__.py
idds/common/plugin/plugin_base.py
idds/common/plugin/plugin_utils.py
idds_common-2.0.9.data/data/tools/env/environment.yml
idds_common-2.0.9.dist-info/LICENSE.rst
idds_common-2.0.9.dist-info/METADATA
idds_common-2.0.9.dist-info/WHEEL
idds_common-2.0.9.dist-info/top_level.txt
idds_common-2.0.9.dist-info/RECORD
